{"id":"a_bc55149ccb2779ff093f","version":1,"createdAt":"2026-07-17T20:51:20.461Z","segments":[{"i":0,"text":"Subject: Enhancing Team Collaboration and Skill Development Through Synergy Sprint Dear Team, I hope this message finds you well. I'm thrilled to announce a significant new initiative, Synergy Sprint, specifically designed to foster enhanced collaboration and accelerate professional growth across all our departments.","words":["Subject","Enhancing","Team","Collaboration","and","Skill","Development","Through","Synergy","Sprint","Dear","Team","I","hope","this","message","finds","you","well","I'm","thrilled","to","announce","a","significant","new","initiative","Synergy","Sprint","specifically","designed","to","foster","enhanced","collaboration","and","accelerate","professional","growth","across","all","our","departments"],"durMs":21384,"startMs":0,"wordIndexStart":0,"wordIndexEnd":43}],"totalMs":21384}